dashfrog/__init__.py
dashfrog/alembic.ini
dashfrog/cli.py
dashfrog/config.py
dashfrog/constants.py
dashfrog/dashfrog.py
dashfrog/flow.py
dashfrog/metrics.py
dashfrog/migrations.py
dashfrog/models.py
dashfrog/py.typed
dashfrog/step.py
dashfrog/utils.py
dashfrog/alembic/env.py
dashfrog/alembic/script.py.mako
dashfrog/alembic/versions/03da39980edf_notebook_extra_cols.py
dashfrog/alembic/versions/874ee482e31f_init_models.py
dashfrog/alembic/versions/9c7749d989a7_notebook_cols.py
dashfrog/alembic/versions/b1446e5041c9_comment_col.py
dashfrog/api/__init__.py
dashfrog/api/auth.py
dashfrog/api/auth_router.py
dashfrog/api/comment.py
dashfrog/api/flow.py
dashfrog/api/metrics.py
dashfrog/api/notebook.py
dashfrog/api/schemas.py
dashfrog/api/static/index.html
dashfrog/api/static/assets/index--t_j4mBk.js
dashfrog/api/static/assets/index-BJ2dj9hy.css
dashfrog/api/static/assets/index-BNdZECzp.css
dashfrog/api/static/assets/index-BQyy4xZc.js
dashfrog/api/static/assets/index-BlFfs7vo.js
dashfrog/api/static/assets/index-BsO8MvyO.js
dashfrog/api/static/assets/index-By0xYddw.js
dashfrog/api/static/assets/index-C66BOw1k.css
dashfrog/api/static/assets/index-C77Elh4e.js
dashfrog/api/static/assets/index-C8Mc4KrH.js
dashfrog/api/static/assets/index-CAGcDdP9.js
dashfrog/api/static/assets/index-CMvZkOeU.css
dashfrog/api/static/assets/index-CSAPXuQt.js
dashfrog/api/static/assets/index-CSHIcrQS.css
dashfrog/api/static/assets/index-CuhZZ-Nz.js
dashfrog/api/static/assets/index-DOOJ5TeS.js
dashfrog/api/static/assets/index-Drm6YCXq.js
dashfrog/api/static/assets/index-zfOez08x.css
dashfrog/api/static/assets/inter-v12-latin-100-46Mq0mOp.woff
dashfrog/api/static/assets/inter-v12-latin-100-BQDzDElq.woff2
dashfrog/api/static/assets/inter-v12-latin-200-BxfrU12A.woff2
dashfrog/api/static/assets/inter-v12-latin-200-DXfqWPZg.woff
dashfrog/api/static/assets/inter-v12-latin-300-DEbyFmpd.woff2
dashfrog/api/static/assets/inter-v12-latin-300-f7r92Nkj.woff
dashfrog-0.1.12.dist-info/METADATA
dashfrog-0.1.12.dist-info/WHEEL
dashfrog-0.1.12.dist-info/entry_points.txt
dashfrog-0.1.12.dist-info/top_level.txt
dashfrog-0.1.12.dist-info/RECORD
